{"CODE": "7.18", "Datensatzbezeichner": "WDVS Verklebung und Beschichtung Kunstharzputz (ohne Daemmmaterial)", "Deklarierte Einheit": "m2", "Umrechnungsfaktor": "", "Gewicht [kg]": "12,48", "Rohdichte [kg/m3]": "", "Flaechengewicht [kg/m2]": "12,48", "Laengengewicht [kg/m]": "", "Umrech-nungsfaktor [pro kg]": "12,48", "PENRT A1-A3 [MJ]": "136,1741637", "PENRT C3 [MJ]": "0", "PENRT C4 [MJ]": "2,732578", "PENRT D1 [MJ]": "0", "GWP A1-A3 [kg CO2e]": "6,70287824", "GWP C3 [kg CO2e]": "0", "GWP C4 [kg CO2e]": "0,187209", "GWP D1 [kg CO2e]": "0", "Bezeichner": "WDVS Kunstharzputz", "Materialgruppe": "WDVS-Putz", "Funktion am und im Gebaeude": "Putz"}