{"CODE": "9.25", "Datensatzbezeichner": "Fugendichtungsbaender Butyl", "Deklarierte Einheit": "kg", "Umrechnungsfaktor": "", "Gewicht [kg]": "1", "Rohdichte [kg/m3]": "1200", "Flaechengewicht [kg/m2]": "", "Laengengewicht [kg/m]": "0,06", "Umrech-nungsfaktor [pro kg]": "1", "PENRT A1-A3 [MJ]": "129,690161", "PENRT C3 [MJ]": "1,437188", "PENRT C4 [MJ]": "0", "PENRT D1 [MJ]": "-20,560994", "GWP A1-A3 [kg CO2e]": "5,68409822", "GWP C3 [kg CO2e]": "3,034756", "GWP C4 [kg CO2e]": "0", "GWP D1 [kg CO2e]": "-1,405431", "Bezeichner": "Fugendichtungsband", "Materialgruppe": "Butyl", "Funktion am und im Gebaeude": "Dichtung"}