{"CODE": "9.40", "Datensatzbezeichner": "Kunststoffprofil CR (Chloropren-Kautschuk)", "Deklarierte Einheit": "kg", "Umrechnungsfaktor": "", "Gewicht [kg]": "1", "Rohdichte [kg/m3]": "1420", "Flaechengewicht [kg/m2]": "", "Laengengewicht [kg/m]": "", "Umrech-nungsfaktor [pro kg]": "1", "PENRT A1-A3 [MJ]": "129,8177935", "PENRT C3 [MJ]": "1,68463", "PENRT C4 [MJ]": "0", "PENRT D1 [MJ]": "-22,27441", "GWP A1-A3 [kg CO2e]": "6,35686193", "GWP C3 [kg CO2e]": "3,561459", "GWP C4 [kg CO2e]": "0", "GWP D1 [kg CO2e]": "-1,522551", "Bezeichner": "Kunststoffprofil CR", "Materialgruppe": "CR-Kautschuk", "Funktion am und im Gebaeude": "Dichtung"}