{"CODE": "1.2", "Datensatzbezeichner": "Kies 2/32 getrocknet", "Deklarierte Einheit": "kg", "Umrechnungsfaktor": "1850", "Gewicht [kg]": "1", "Rohdichte [kg/m3]": "1850", "Flaechengewicht [kg/m2]": "", "Laengengewicht [kg/m]": "", "Umrech-nungsfaktor [pro kg]": "1", "PENRT A1-A3 [MJ]": "0,54252315", "PENRT C3 [MJ]": "0,121834", "PENRT C4 [MJ]": "0", "PENRT D1 [MJ]": "-0,027409", "GWP A1-A3 [kg CO2e]": "0,03325947", "GWP C3 [kg CO2e]": "0,007337", "GWP C4 [kg CO2e]": "0", "GWP D1 [kg CO2e]": "-0,002054", "Bezeichner": "Kies 2/32 getrocknet", "Materialgruppe": "Kies getrocknet", "Funktion am und im Gebaeude": "Schuettung"}